{
  "pageId": "service.sales-qualified-lead-generation",
  "pageName": "Sales Qualified Lead Generation",
  "pageType": "serviceHub",
  "seo": {
    "canonicalPath": "/services/sales-qualified-lead-generation",
    "description": "Enterprise sales qualified lead generation, verified decision-makers, BANT/CHAMP qualification, intent signals, and CRM-ready prospect profiles. Leads your sales team can act on immediately.",
    "focusKeyphrase": "sales qualified lead generation",
    "secondaryKeywords": [
      "B2B SQL generation",
      "active prospecting B2B",
      "qualified B2B leads",
      "exhibition lead generation company"
    ],
    "title": "Sales Qualified Lead Generation for Enterprise B2B | B2B Sales Arrow"
  }
}
