{
  "heading": "Explore What We Do Best",
  "ctaLabel": "Learn More",
  "eyebrow": "WHILE YOU WAIT",
  "serviceLabel": "Service",
  "services": [
    {
      "color": "bg-brand-blue",
      "description": "End-to-end exhibition management across 40+ countries, from booth design to on-floor lead capture.",
      "icon": "Globe",
      "id": "global-events",
      "image": "/images/home/hero/home_hero_bg.avif",
      "title": "Global Event Solutions"
    },
    {
      "color": "bg-brand-cyan",
      "description": "Cinematic brand storytelling and high-fidelity corporate content that builds authority.",
      "icon": "MonitorPlay",
      "id": "media",
      "image": "/images/home/services/corporate-media-production.avif",
      "title": "Media Production"
    },
    {
      "color": "bg-brand-primary",
      "description": "Data-driven SEO, paid advertising, and LinkedIn campaigns engineered to scale enterprise pipeline.",
      "icon": "Rocket",
      "id": "performance",
      "image": "/images/home/services/digital-marketing.avif",
      "title": "Digital Marketing"
    },
    {
      "color": "bg-brand-blue",
      "description": "Precision-targeted acquisition strategies for high-value B2B accounts ready to buy.",
      "icon": "Users",
      "id": "lead-gen",
      "image": "/images/home/services/active-prospecting.avif",
      "title": "Sales Qualified Lead Generation"
    },
    {
      "color": "bg-brand-cyan",
      "description": "Human-powered intelligence, data augmentation, and validation to fuel confident decisions.",
      "icon": "Lightbulb",
      "id": "market-research",
      "image": "/images/home/services/database-and-market-research.avif",
      "title": "Market Research"
    }
  ]
}
