{
  "description": "Trusted across 30+ countries, we deliver custom trade show booth design, active on-ground prospecting, and end-to-end event execution that turns exhibitions into a qualified B2B sales pipeline.",
  "eyebrow": "GLOBAL CAPABILITY. STRATEGIC GROWTH.",
  "mobileVideoUrl": "/media/home/hero/mobile.mp4",
  "mobileVideoWebm": "/media/home/hero/mobile.webm",
  "primaryCta": {
    "href": "/contact-us",
    "label": "Get a Custom Proposal"
  },
  "rotatingWords": [
    "Trade Show Booth Solutions",
    "Corporate Video Production",
    "Event Video Production",
    "On-Ground Lead Generation",
    "Experience Creation",
    "Event Branding Solutions",
    "Performance Marketing"
  ],
  "title": "Enhance Your B2B Events with One Complete Partner",
  "videoUrl": "/media/home/hero/desktop.mp4",
  "videoWebm": "/media/home/hero/desktop.webm"
}
